vaccine_feed_ingest_schema/__init__.py
vaccine_feed_ingest_schema/common.py
vaccine_feed_ingest_schema/load.py
vaccine_feed_ingest_schema/location.py
vaccine_feed_ingest_schema/schema.py
vaccine_feed_ingest_schema-1.2.5.dist-info/LICENSE
vaccine_feed_ingest_schema-1.2.5.dist-info/METADATA
vaccine_feed_ingest_schema-1.2.5.dist-info/WHEEL
vaccine_feed_ingest_schema-1.2.5.dist-info/top_level.txt
vaccine_feed_ingest_schema-1.2.5.dist-info/RECORD
