Metadata-Version: 2.1
Name: vaccine-feed-ingest-schema
Version: 1.2.5
Summary: Normalized data schema for the output of the vaccine-feed-ingest pipeline.
Home-page: https://github.com/CAVaccineInventory/vaccine-feed-ingest-schema
Author: Vaccinate The States
License: MIT
Project-URL: Issues, https://github.com/CAVaccineInventory/vaccine-feed-ingest-schema/issues
Project-URL: CI, https://github.com/CAVaccineInventory/vaccine-feed-ingest-schema/actions
Project-URL: Changelog, https://github.com/CAVaccineInventory/vaccine-feed-ingest-schema/releases
Platform: UNKNOWN
Requires-Python: >=3.8
Requires-Dist: pydantic[email]
Provides-Extra: lint
Requires-Dist: flake8 ; extra == 'lint'
Requires-Dist: black ; extra == 'lint'
Requires-Dist: mypy ; extra == 'lint'
Requires-Dist: isort ; extra == 'lint'
Provides-Extra: test
Requires-Dist: pytest ; extra == 'test'
